<?xml version="1.0" encoding="utf-8"?>
<mujoco>
    <compiler angle="radian" coordinate="local" meshdir="../stls/fetch" texturedir="../textures"></compiler>
    <option timestep="0.002">
        <flag warmstart="enable"></flag>
    </option>

    <include file="shared.xml"></include>
    
    <worldbody>
        <geom name="floor0" pos="1.42 0.75 0" size="1.0 0.7 1" type="plane" condim="3" material="floor_mat"></geom>
        <body name="floor0" pos="1.42 0.75 0">
            <site name="target0" pos="0 0 0.5" size="0.02 0.02 0.02" rgba="1 0 0 1" type="sphere"></site>
        </body>

        <include file="robot.xml"></include>
        
        <body pos="1.65 0.75 0.2" name="table0">
            <geom size="0.5 0.45 0.2" type="box" mass="20000" material="table_mat"></geom><geom size="0.03150302926816991 0.04584352824577212 0.0016400228291436946" pos="0.21622250471400234 0.025724429998833676 0.2016400228291437" type="box" mass="200" rgba="0.4 0.4 0.4 1"></geom>
<geom size="0.0326576714464089 0.017552084298397923 0.009036739216449853" pos="-0.17582954572506881 -0.1693929953764526 0.20903673921644986" type="box" mass="200" rgba="0.4 0.4 0.4 1"></geom>
<geom size="0.027619108509492122 0.0036258273963848367 0.003356933647084242" pos="0.08458164602360635 -0.14252057007479293 0.20335693364708426" type="box" mass="200" rgba="0.4 0.4 0.4 1"></geom>
<geom size="0.03308545276845943 0.02347754802734193 0.005661238585901865" pos="-0.16055312534382177 -0.26111534104375866 0.20566123858590188" type="box" mass="200" rgba="0.4 0.4 0.4 1"></geom>
<geom size="0.033848395592107866 0.02231652789495361 0.004482557971387187" pos="0.26743032461881505 -0.04090438903064886 0.2044825579713872" type="box" mass="200" rgba="0.4 0.4 0.4 1"></geom>
<geom size="0.032254762477509115 0.04439566692220933 0.008012594274625067" pos="0.16177554360827678 0.1923713877067435 0.20801259427462507" type="box" mass="200" rgba="0.4 0.4 0.4 1"></geom>
<geom size="0.03087327714167649 0.018633750631647062 0.0037594149230159584" pos="-0.2631226437436489 0.25411127970734265 0.20375941492301597" type="box" mass="200" rgba="0.4 0.4 0.4 1"></geom>
<geom size="0.022973783705333522 0.03876898620220985 0.001179000580048056" pos="-0.1080197199937862 -0.009305962510333554 0.20117900058004806" type="box" mass="200" rgba="0.4 0.4 0.4 1"></geom>
<geom size="0.048490436842848074 0.02089304738822724 0.0032102828528807227" pos="0.1991571517291469 0.26314139027430244 0.20321028285288073" type="box" mass="200" rgba="0.4 0.4 0.4 1"></geom>
<geom size="0.019069388316423984 0.042624374605960816 0.005598727065985713" pos="-0.10893790519168203 -0.049847286907620636 0.20559872706598573" type="box" mass="200" rgba="0.4 0.4 0.4 1"></geom>
<geom size="0.04463070611967826 0.022097265662745006 0.006732417923554485" pos="0.13570111668925844 0.12122064786269388 0.20673241792355448" type="box" mass="200" rgba="0.4 0.4 0.4 1"></geom>
<geom size="0.04401373016635479 0.041694311561893176 0.0076061327714917505" pos="-0.1866901738755689 0.19122053336574008 0.20760613277149176" type="box" mass="200" rgba="0.4 0.4 0.4 1"></geom>
<geom size="0.021994876007642793 0.04447883994836292 0.006699672670400987" pos="-0.17001630629132106 0.18654090538918638 0.20669967267040099" type="box" mass="200" rgba="0.4 0.4 0.4 1"></geom>
<geom size="0.028278728195454548 0.005468405188933065 0.006255963010289109" pos="-0.14841216489727568 -0.07156833111419075 0.20625596301028912" type="box" mass="200" rgba="0.4 0.4 0.4 1"></geom>
<geom size="0.04704005190886011 0.04480635030799707 0.0031778794976989656" pos="0.2306519174565313 -0.2707007214084143 0.20317787949769897" type="box" mass="200" rgba="0.4 0.4 0.4 1"></geom>
<geom size="0.009541896890990307 0.012550062457520585 0.007169242825599594" pos="-0.11993361028128663 -0.2027299643088229 0.2071692428255996" type="box" mass="200" rgba="0.4 0.4 0.4 1"></geom>
<geom size="0.04069857668846873 0.017142186969345115 0.003390295571599916" pos="-0.13326623932993356 0.261790212906506 0.20339029557159993" type="box" mass="200" rgba="0.4 0.4 0.4 1"></geom>
<geom size="0.024294461990833006 0.010415442242082344 0.001628501842697169" pos="0.09092656951192424 0.10683775632149028 0.20162850184269718" type="box" mass="200" rgba="0.4 0.4 0.4 1"></geom>
<geom size="0.01927669159221189 0.028040088837712054 0.007826099306418699" pos="0.04924556244274786 0.1468721755908815 0.2078260993064187" type="box" mass="200" rgba="0.4 0.4 0.4 1"></geom>
<geom size="0.015084844056275495 0.04703941383098954 0.005570446501005938" pos="-0.08663867578129403 -0.022619885677617635 0.20557044650100595" type="box" mass="200" rgba="0.4 0.4 0.4 1"></geom>
<geom size="0.04134098876832517 0.007647471058016257 0.002689372545712274" pos="0.15204513558506605 -0.2270164483863741 0.2026893725457123" type="box" mass="200" rgba="0.4 0.4 0.4 1"></geom>
<geom size="0.012105655056369336 0.03821808054905771 0.005869669982053684" pos="-0.05969029589989133 0.019815506954295736 0.2058696699820537" type="box" mass="200" rgba="0.4 0.4 0.4 1"></geom>
<geom size="0.015040610186702337 0.040904562411630326 0.005156356014928747" pos="-0.10427444532478991 0.07203871728694916 0.20515635601492876" type="box" mass="200" rgba="0.4 0.4 0.4 1"></geom>
<geom size="0.012659136743262453 0.005932741789091145 0.005944057635283974" pos="0.05380549333998352 -0.06775016203545073 0.20594405763528398" type="box" mass="200" rgba="0.4 0.4 0.4 1"></geom>
<geom size="0.012497213676979365 0.04603237823835491 0.002827419400833028" pos="-0.050046719223895086 -0.2794065215556852 0.20282741940083304" type="box" mass="200" rgba="0.4 0.4 0.4 1"></geom>
<geom size="0.016419821291720996 0.0029701423432353393 0.0035110920859302563" pos="0.030075674872040825 0.010087085389528183 0.20351109208593027" type="box" mass="200" rgba="0.4 0.4 0.4 1"></geom>
<geom size="0.04551214710541073 0.04169593616988761 0.006049626192694821" pos="0.01861192883579177 -0.030363469119127295 0.20604962619269485" type="box" mass="200" rgba="0.4 0.4 0.4 1"></geom>
<geom size="0.011104073272990431 0.026647181101546964 0.0013231955317789075" pos="-0.1862954320055215 0.019819587995989485 0.2013231955317789" type="box" mass="200" rgba="0.4 0.4 0.4 1"></geom>
<geom size="0.033006858888426666 0.016390565430863653 0.003321885213128136" pos="0.15436797174280725 0.16452810795165207 0.20332188521312813" type="box" mass="200" rgba="0.4 0.4 0.4 1"></geom>
<geom size="0.04719307074153973 0.04340193711250415 0.006029130552449175" pos="0.07813497359065402 0.27923672258474114 0.20602913055244917" type="box" mass="200" rgba="0.4 0.4 0.4 1"></geom>
        </body>
        
        <body name="object0" pos="0.025 0.025 0.025">
            <joint name="object0:joint" type="free" damping="0.01"></joint>
            <geom size="0.025740238310394126 0.025740238310394126 0.025740238310394126" type="sphere" condim="3" name="object0" material="block_mat" mass="10.857851624671484" rgba="0.4 0.4 0.8 1"></geom>
            <site name="object0" pos="0 0 0" size="0.002 0.002 0.002" rgba="1 0 0 1" type="sphere"></site>
        </body>

        <body name="stick" pos="1.0 0.025 0.025">
            <joint name="stick:joint" type="free" damping="0.01"></joint>
            <geom size="0.4 0.015 0.015" type="box" condim="3" name="stick" material="block_mat" mass="2"></geom>
            <site name="stick" pos="-0.25 0 0" size="0.002 0.002 0.002" rgba="1 0 0 1" type="sphere"></site>
        </body>

        <light directional="true" ambient="0.2 0.2 0.2" diffuse="0.8 0.8 0.8" specular="0.3 0.3 0.3" castshadow="false" pos="0 0 4" dir="0 0 -1" name="light0"></light>
    </worldbody>
    
    <actuator>
        <position ctrllimited="true" ctrlrange="0 0.2" joint="robot0:l_gripper_finger_joint" kp="30000" name="robot0:l_gripper_finger_joint" user="1"></position>
        <position ctrllimited="true" ctrlrange="0 0.2" joint="robot0:r_gripper_finger_joint" kp="30000" name="robot0:r_gripper_finger_joint" user="1"></position>
    </actuator>
</mujoco>
    