<?xml version="1.0" encoding="utf-8"?>
<mujoco>
    <compiler angle="radian" coordinate="local" meshdir="../stls/fetch" texturedir="../textures"></compiler>
    <option timestep="0.002">
        <flag warmstart="enable"></flag>
    </option>

    <include file="shared.xml"></include>
    
    <worldbody>
        <geom name="floor0" pos="1.42 0.75 0" size="1.0 0.7 1" type="plane" condim="3" material="floor_mat"></geom>
        <body name="floor0" pos="1.42 0.75 0">
            <site name="target0" pos="0 0 0.5" size="0.02 0.02 0.02" rgba="1 0 0 1" type="sphere"></site>
        </body>

        <include file="robot.xml"></include>
        
        <body pos="1.65 0.75 0.2" name="table0">
            <geom size="0.5 0.45 0.2" type="box" mass="20000" material="table_mat"></geom><geom size="0.043728155757090055 0.04095041125547585 0.00790665383547713" pos="0.05334391849719117 -0.23602039903209016 0.20790665383547713" type="box" mass="200" rgba="0.4 0.4 0.4 1"></geom>
<geom size="0.03469967847502277 0.01581375327927211 0.007855608029011592" pos="-0.0799879297119799 -0.2193563790360905 0.2078556080290116" type="box" mass="200" rgba="0.4 0.4 0.4 1"></geom>
<geom size="0.030660112118833398 0.044257465449561766 0.0018409953630942131" pos="-0.12334445008444453 -0.14133961028217773 0.20184099536309422" type="box" mass="200" rgba="0.4 0.4 0.4 1"></geom>
<geom size="0.039331581054293636 0.00845678641675325 0.004459857452497759" pos="-0.07403830101178685 0.1615985370411146 0.20445985745249778" type="box" mass="200" rgba="0.4 0.4 0.4 1"></geom>
<geom size="0.02253121287041258 0.01319636506725741 0.0008981027385299819" pos="-0.008508359749004157 -0.15058985959410034 0.20089810273852998" type="box" mass="200" rgba="0.4 0.4 0.4 1"></geom>
<geom size="0.03458983348831839 0.012764073625451115 0.005416212983974586" pos="0.08194178971248922 0.2404066447135565 0.2054162129839746" type="box" mass="200" rgba="0.4 0.4 0.4 1"></geom>
<geom size="0.045363860545573655 0.03375642535113352 0.0022129170399162582" pos="-0.2638650232974634 0.1513304698062905 0.20221291703991626" type="box" mass="200" rgba="0.4 0.4 0.4 1"></geom>
<geom size="0.018639008742106968 0.006913194334055206 0.00836879586434455" pos="0.02223901983104104 0.2694073825758318 0.20836879586434456" type="box" mass="200" rgba="0.4 0.4 0.4 1"></geom>
<geom size="0.029364844257335144 0.04761273361907697 0.005530454662354551" pos="-0.19680719554863063 0.2783819658455661 0.20553045466235456" type="box" mass="200" rgba="0.4 0.4 0.4 1"></geom>
<geom size="0.005400221401943999 0.009950054495758538 0.009959438556978267" pos="0.1671580939193097 0.20449609013476772 0.20995943855697827" type="box" mass="200" rgba="0.4 0.4 0.4 1"></geom>
<geom size="0.02410280816454198 0.019555302878987456 0.002788020328764318" pos="-0.267699591651029 -0.27160957463763846 0.20278802032876433" type="box" mass="200" rgba="0.4 0.4 0.4 1"></geom>
<geom size="0.01707141622710108 0.01196997742989549 0.006701211138149555" pos="-0.19822745863263613 0.24543036456472472 0.20670121113814957" type="box" mass="200" rgba="0.4 0.4 0.4 1"></geom>
<geom size="0.0484186006315726 0.02426971901102785 0.0006060508542462515" pos="-0.19761934114374033 -0.13969496130779566 0.20060605085424627" type="box" mass="200" rgba="0.4 0.4 0.4 1"></geom>
<geom size="0.04392292141831928 0.044525179109809285 0.009666341221620535" pos="-0.14241260904476852 -0.19450704017919312 0.20966634122162053" type="box" mass="200" rgba="0.4 0.4 0.4 1"></geom>
<geom size="0.02671656313284859 0.01787356878981819 0.004041500544219947" pos="-0.02856542737953277 -0.26345948917724543 0.20404150054421996" type="box" mass="200" rgba="0.4 0.4 0.4 1"></geom>
<geom size="0.016905383478761405 0.03741743408995818 0.0048387154266619995" pos="0.15929448631117904 0.10340365759853865 0.20483871542666202" type="box" mass="200" rgba="0.4 0.4 0.4 1"></geom>
<geom size="0.04711678256581927 0.0348271658088875 0.005639538105996269" pos="-0.20569711414137026 0.25266342099267086 0.20563953810599628" type="box" mass="200" rgba="0.4 0.4 0.4 1"></geom>
<geom size="0.04983928715748615 0.042281407834212845 0.0010254427930566213" pos="-0.23314655597626915 -0.08105072860259765 0.20102544279305662" type="box" mass="200" rgba="0.4 0.4 0.4 1"></geom>
<geom size="0.03510514239844676 0.041518319128235635 0.0018900708381070924" pos="0.07514422665192805 -0.2042601104418466 0.20189007083810712" type="box" mass="200" rgba="0.4 0.4 0.4 1"></geom>
<geom size="0.00649309828406166 0.02407764179259455 0.008624334504563416" pos="0.07662339817042135 0.10892619024946643 0.2086243345045634" type="box" mass="200" rgba="0.4 0.4 0.4 1"></geom>
<geom size="0.02026514137007119 0.014077137937537784 0.009327755149828459" pos="-0.05315491689641616 0.008042701687302256 0.20932775514982846" type="box" mass="200" rgba="0.4 0.4 0.4 1"></geom>
<geom size="0.004538878648316355 0.004388418113499728 0.007604833385714441" pos="0.25920360098655265 0.0820172440565306 0.20760483338571445" type="box" mass="200" rgba="0.4 0.4 0.4 1"></geom>
<geom size="0.04510223293557694 0.03892368429586293 0.0013757670120308502" pos="-0.26000558033053184 0.2652535794956526 0.20137576701203086" type="box" mass="200" rgba="0.4 0.4 0.4 1"></geom>
<geom size="0.008918600969641595 0.03182865209511087 0.002434080034504016" pos="0.009328878229046655 -0.00748566055619293 0.20243408003450403" type="box" mass="200" rgba="0.4 0.4 0.4 1"></geom>
<geom size="0.03621773552268882 0.04120632734382179 0.009988662888651018" pos="-0.17488339079821766 -0.03800191628521565 0.20998866288865103" type="box" mass="200" rgba="0.4 0.4 0.4 1"></geom>
<geom size="0.019424411465802684 0.00265592154942016 0.002444587534310583" pos="0.0278692627465284 0.2261660387494015 0.2024445875343106" type="box" mass="200" rgba="0.4 0.4 0.4 1"></geom>
<geom size="0.016376088137914257 0.03536971642187356 0.009406967861147957" pos="-0.19237986510559874 -0.23485764934894404 0.20940696786114796" type="box" mass="200" rgba="0.4 0.4 0.4 1"></geom>
<geom size="0.04934035095880659 0.003451268662771915 0.0028819699422199204" pos="0.22160386876545707 -0.13474784738152107 0.20288196994221994" type="box" mass="200" rgba="0.4 0.4 0.4 1"></geom>
        </body>
        
        <body name="object0" pos="0.025 0.025 0.025">
            <joint name="object0:joint" type="free" damping="0.01"></joint>
            <geom size="0.020534396580275463 0.020534396580275463 0.020534396580275463" type="sphere" condim="3" name="object0" material="block_mat" mass="13.194787615410629" rgba="0.4 0.4 0.8 1"></geom>
            <site name="object0" pos="0 0 0" size="0.002 0.002 0.002" rgba="1 0 0 1" type="sphere"></site>
        </body>

        <body name="stick" pos="1.0 0.025 0.025">
            <joint name="stick:joint" type="free" damping="0.01"></joint>
            <geom size="0.4 0.015 0.015" type="box" condim="3" name="stick" material="block_mat" mass="2"></geom>
            <site name="stick" pos="-0.25 0 0" size="0.002 0.002 0.002" rgba="1 0 0 1" type="sphere"></site>
        </body>

        <light directional="true" ambient="0.2 0.2 0.2" diffuse="0.8 0.8 0.8" specular="0.3 0.3 0.3" castshadow="false" pos="0 0 4" dir="0 0 -1" name="light0"></light>
    </worldbody>
    
    <actuator>
        <position ctrllimited="true" ctrlrange="0 0.2" joint="robot0:l_gripper_finger_joint" kp="30000" name="robot0:l_gripper_finger_joint" user="1"></position>
        <position ctrllimited="true" ctrlrange="0 0.2" joint="robot0:r_gripper_finger_joint" kp="30000" name="robot0:r_gripper_finger_joint" user="1"></position>
    </actuator>
</mujoco>
    