<?xml version="1.0" encoding="utf-8"?>
<mujoco>
    <compiler angle="radian" coordinate="local" meshdir="../stls/fetch" texturedir="../textures"></compiler>
    <option timestep="0.002">
        <flag warmstart="enable"></flag>
    </option>

    <include file="shared.xml"></include>
    
    <worldbody>
        <geom name="floor0" pos="1.42 0.75 0" size="1.0 0.7 1" type="plane" condim="3" material="floor_mat"></geom>
        <body name="floor0" pos="1.42 0.75 0">
            <site name="target0" pos="0 0 0.5" size="0.02 0.02 0.02" rgba="1 0 0 1" type="sphere"></site>
        </body>

        <include file="robot.xml"></include>
        
        <body pos="1.65 0.75 0.2" name="table0">
            <geom size="0.5 0.45 0.2" type="box" mass="20000" material="table_mat"></geom><geom size="0.0343230093622524 0.03207606172281254 0.004095725105131165" pos="-0.02530481330449791 -0.13720950079451252 0.2040957251051312" type="box" mass="200" rgba="0.4 0.4 0.4 1"></geom>
<geom size="0.021594786625340336 0.023516894132753163 0.0010721636287282707" pos="0.12610171026596884 -0.22666027374868467 0.2010721636287283" type="box" mass="200" rgba="0.4 0.4 0.4 1"></geom>
<geom size="0.03544604114058681 0.041284171484942116 0.008037871304044182" pos="0.13145323342088994 -0.19883473184870792 0.2080378713040442" type="box" mass="200" rgba="0.4 0.4 0.4 1"></geom>
<geom size="0.002145111524594087 0.04728386328352367 0.00627959161537056" pos="0.25439842531269014 -0.035899607889680274 0.20627959161537057" type="box" mass="200" rgba="0.4 0.4 0.4 1"></geom>
<geom size="0.016099072576266756 0.021755958481778644 0.006937841255481297" pos="0.1539385314201952 0.07151855276542168 0.20693784125548131" type="box" mass="200" rgba="0.4 0.4 0.4 1"></geom>
<geom size="0.016156595310852968 0.0396902919854276 0.005246659704951289" pos="0.2308209359893299 0.09865823174039773 0.2052466597049513" type="box" mass="200" rgba="0.4 0.4 0.4 1"></geom>
<geom size="0.027275234012573663 0.030894904286214414 0.0037575472370544546" pos="-0.06812393307875025 0.012026862802429705 0.20375754723705447" type="box" mass="200" rgba="0.4 0.4 0.4 1"></geom>
<geom size="0.043312481470632117 0.03590813074136114 0.0005419235298933113" pos="0.10751689945768228 0.15661175022205115 0.20054192352989333" type="box" mass="200" rgba="0.4 0.4 0.4 1"></geom>
<geom size="0.02823158251714847 0.03461382070444779 0.007221580767946399" pos="0.15003919253883546 -0.12072425446905813 0.20722158076794642" type="box" mass="200" rgba="0.4 0.4 0.4 1"></geom>
<geom size="0.00909841455667576 0.005900726487126025 0.005331616348321475" pos="0.1768559276971497 0.013036388116394737 0.20533161634832148" type="box" mass="200" rgba="0.4 0.4 0.4 1"></geom>
<geom size="0.026119601072012114 0.01643249323055612 0.009813536721700804" pos="-0.16109980746730299 -0.036257005727557745 0.2098135367217008" type="box" mass="200" rgba="0.4 0.4 0.4 1"></geom>
<geom size="0.028236196833441717 0.03923714900790635 0.008598037888292788" pos="0.07805007460125901 0.04809170271118279 0.2085980378882928" type="box" mass="200" rgba="0.4 0.4 0.4 1"></geom>
<geom size="0.04132744914363174 0.040146382245694084 0.003237639577120606" pos="-0.024648941979006744 -0.26276533639765054 0.20323763957712063" type="box" mass="200" rgba="0.4 0.4 0.4 1"></geom>
<geom size="0.03951275566979784 0.009310051796296518 0.005078077447369038" pos="0.10536644947247281 -0.24358485609153677 0.20507807744736906" type="box" mass="200" rgba="0.4 0.4 0.4 1"></geom>
<geom size="0.017963161215051485 0.007673555151408368 0.004319706342328699" pos="-0.14441620302984892 -0.10250626122455492 0.2043197063423287" type="box" mass="200" rgba="0.4 0.4 0.4 1"></geom>
<geom size="0.009742699945614778 0.0063172125573267126 0.005138272616909606" pos="-0.07462287415677321 0.26955334397335323 0.20513827261690962" type="box" mass="200" rgba="0.4 0.4 0.4 1"></geom>
<geom size="0.021729782717985924 0.0018941423055520174 0.0011118981672933743" pos="-0.20887492076139746 -0.28185712904338095 0.20111189816729338" type="box" mass="200" rgba="0.4 0.4 0.4 1"></geom>
<geom size="0.0224293997714281 0.018040609013571452 0.0018048510761300676" pos="-0.19283489546879728 0.23099548685937904 0.20180485107613008" type="box" mass="200" rgba="0.4 0.4 0.4 1"></geom>
<geom size="0.03866377500264106 0.04389920054465285 0.008042175499269236" pos="0.18915631391971827 -0.271883945478364 0.20804217549926923" type="box" mass="200" rgba="0.4 0.4 0.4 1"></geom>
<geom size="0.02041105504617262 0.017021960087564084 0.00875219628429099" pos="-0.14014071918937868 -0.15822594653073557 0.208752196284291" type="box" mass="200" rgba="0.4 0.4 0.4 1"></geom>
<geom size="0.016738581065065976 0.024374344550182156 0.007529546843333132" pos="-0.25343253448799186 0.20711199930504326 0.20752954684333313" type="box" mass="200" rgba="0.4 0.4 0.4 1"></geom>
        </body>
        
        <body name="object0" pos="0.025 0.025 0.025">
            <joint name="object0:joint" type="free" damping="0.01"></joint>
            <geom size="0.02126860834623175 0.02126860834623175 0.02126860834623175" type="sphere" condim="3" name="object0" material="block_mat" mass="18.074452959688177" rgba="0.4 0.4 0.8 1"></geom>
            <site name="object0" pos="0 0 0" size="0.002 0.002 0.002" rgba="1 0 0 1" type="sphere"></site>
        </body>

        <body name="stick" pos="1.0 0.025 0.025">
            <joint name="stick:joint" type="free" damping="0.01"></joint>
            <geom size="0.4 0.015 0.015" type="box" condim="3" name="stick" material="block_mat" mass="2"></geom>
            <site name="stick" pos="-0.25 0 0" size="0.002 0.002 0.002" rgba="1 0 0 1" type="sphere"></site>
        </body>

        <light directional="true" ambient="0.2 0.2 0.2" diffuse="0.8 0.8 0.8" specular="0.3 0.3 0.3" castshadow="false" pos="0 0 4" dir="0 0 -1" name="light0"></light>
    </worldbody>
    
    <actuator>
        <position ctrllimited="true" ctrlrange="0 0.2" joint="robot0:l_gripper_finger_joint" kp="30000" name="robot0:l_gripper_finger_joint" user="1"></position>
        <position ctrllimited="true" ctrlrange="0 0.2" joint="robot0:r_gripper_finger_joint" kp="30000" name="robot0:r_gripper_finger_joint" user="1"></position>
    </actuator>
</mujoco>
    