<?xml version="1.0" encoding="utf-8"?>
<mujoco>
    <compiler angle="radian" coordinate="local" meshdir="../stls/fetch" texturedir="../textures"></compiler>
    <option timestep="0.002">
        <flag warmstart="enable"></flag>
    </option>

    <include file="shared.xml"></include>
    
    <worldbody>
        <geom name="floor0" pos="1.42 0.75 0" size="1.0 0.7 1" type="plane" condim="3" material="floor_mat"></geom>
        <body name="floor0" pos="1.42 0.75 0">
            <site name="target0" pos="0 0 0.5" size="0.02 0.02 0.02" rgba="1 0 0 1" type="sphere"></site>
        </body>

        <include file="robot.xml"></include>
        
        <body pos="1.65 0.75 0.2" name="table0">
            <geom size="0.5 0.45 0.2" type="box" mass="20000" material="table_mat"></geom><geom size="0.04371825602940232 0.010507361139647169 0.002525091681843063" pos="0.06191385264915006 -0.02001711722764421 0.20252509168184307" type="box" mass="200" rgba="0.4 0.4 0.4 1"></geom>
<geom size="0.018626347874267517 0.048298105370943464 0.002225728759665936" pos="0.21065098445276792 0.06323625184151516 0.20222572875966593" type="box" mass="200" rgba="0.4 0.4 0.4 1"></geom>
<geom size="0.03507447874682078 0.03891975133590706 0.004764354983798275" pos="0.28470397694925337 -0.011749427782168642 0.20476435498379827" type="box" mass="200" rgba="0.4 0.4 0.4 1"></geom>
<geom size="0.014849550444672784 0.045404674905598144 0.004881810239611206" pos="0.2570928712128589 0.018595483872101692 0.20488181023961122" type="box" mass="200" rgba="0.4 0.4 0.4 1"></geom>
<geom size="0.012099918538591943 0.017851323410096143 0.009822625090253664" pos="-0.1739629961546945 -0.082529076327258 0.20982262509025368" type="box" mass="200" rgba="0.4 0.4 0.4 1"></geom>
<geom size="0.015133217652273899 0.03608394761876078 0.0023939586550936597" pos="0.19904815861467712 0.27516102733261244 0.20239395865509366" type="box" mass="200" rgba="0.4 0.4 0.4 1"></geom>
<geom size="0.021408080055990365 0.025177494057907486 0.007888947307656421" pos="-0.03509877677609935 -0.2582770178571062 0.20788894730765645" type="box" mass="200" rgba="0.4 0.4 0.4 1"></geom>
<geom size="0.027641177285945878 0.026587591653025155 0.004250362476702655" pos="-0.12630482716296001 -0.15340310932692916 0.20425036247670267" type="box" mass="200" rgba="0.4 0.4 0.4 1"></geom>
<geom size="0.027218326456525985 0.008669597606643493 0.0013837958657419737" pos="-0.005711624167007712 -0.0799713066481599 0.20138379586574198" type="box" mass="200" rgba="0.4 0.4 0.4 1"></geom>
<geom size="0.03931157337235115 0.02020370095112223 0.009090538153652305" pos="-0.2072835395175751 0.24778068330054087 0.2090905381536523" type="box" mass="200" rgba="0.4 0.4 0.4 1"></geom>
<geom size="0.009589765044816213 0.012312693218778595 0.002228199085395125" pos="0.17019250541157083 -0.04804810352922434 0.20222819908539513" type="box" mass="200" rgba="0.4 0.4 0.4 1"></geom>
<geom size="0.04276291702894893 0.03314670770797695 0.0011671198339979082" pos="-0.2845697647195268 0.053866389739026466 0.20116711983399793" type="box" mass="200" rgba="0.4 0.4 0.4 1"></geom>
<geom size="0.04481121335931841 0.011952485638938564 0.004516429830090337" pos="-0.27313028919414123 -0.010070226913282077 0.20451642983009036" type="box" mass="200" rgba="0.4 0.4 0.4 1"></geom>
<geom size="0.04018333317830063 0.024487399717649044 0.004396171487893732" pos="-0.15347854399602795 0.020779816092188985 0.20439617148789374" type="box" mass="200" rgba="0.4 0.4 0.4 1"></geom>
<geom size="0.042174725051448876 0.027877378421854657 0.0030032729049652308" pos="0.17257741876120097 -0.23414148779664887 0.20300327290496525" type="box" mass="200" rgba="0.4 0.4 0.4 1"></geom>
<geom size="0.002748208078490199 0.010736164218878994 0.005351892046977554" pos="-0.1220371424693068 0.10955557934365312 0.20535189204697757" type="box" mass="200" rgba="0.4 0.4 0.4 1"></geom>
<geom size="0.04223814267450115 0.016564794546747957 0.007540217977957223" pos="-0.15371795271918923 0.19296926476394483 0.20754021797795724" type="box" mass="200" rgba="0.4 0.4 0.4 1"></geom>
<geom size="0.046260462760277996 0.020595174182828403 0.0009778925090951698" pos="-0.05743796099796519 -0.07617590028705648 0.20097789250909517" type="box" mass="200" rgba="0.4 0.4 0.4 1"></geom>
<geom size="0.025962649883531766 0.02540728531418637 0.008761987845600828" pos="0.07165694207077494 -0.253836271820247 0.20876198784560085" type="box" mass="200" rgba="0.4 0.4 0.4 1"></geom>
<geom size="0.03311747830101317 0.039486697847504144 0.00163275884825868" pos="-0.17313312508596418 0.24602284680976777 0.20163275884825868" type="box" mass="200" rgba="0.4 0.4 0.4 1"></geom>
<geom size="0.04777130067396916 0.005686991473453627 0.009274413542160015" pos="0.29961664249865533 -0.019885644209657716 0.20927441354216003" type="box" mass="200" rgba="0.4 0.4 0.4 1"></geom>
<geom size="0.04166430523305457 0.01050279481475732 0.004835836794388311" pos="-0.2331545989145108 0.11949736536252326 0.20483583679438833" type="box" mass="200" rgba="0.4 0.4 0.4 1"></geom>
<geom size="0.019763647467413395 0.008164445161359026 0.0022970275799358377" pos="-0.22127943283498352 -0.08922959016747825 0.20229702757993584" type="box" mass="200" rgba="0.4 0.4 0.4 1"></geom>
<geom size="0.0423311759831752 0.023746572877268085 0.006724251333392364" pos="0.27335633011510146 0.11778829971857058 0.20672425133339237" type="box" mass="200" rgba="0.4 0.4 0.4 1"></geom>
<geom size="0.012898389680381588 0.00497601167112483 0.008241658155569756" pos="-0.13245181787936958 0.07623284546841197 0.20824165815556978" type="box" mass="200" rgba="0.4 0.4 0.4 1"></geom>
<geom size="0.045966261831357776 0.026789013318148185 0.00520224652750558" pos="-0.07034579764599447 -0.006974046356577723 0.2052022465275056" type="box" mass="200" rgba="0.4 0.4 0.4 1"></geom>
<geom size="0.03417253583564581 0.03137384700353717 0.008706054256182367" pos="0.2938192214435604 -0.048447042883960734 0.20870605425618238" type="box" mass="200" rgba="0.4 0.4 0.4 1"></geom>
<geom size="0.04902458967658532 0.0335708673337785 0.0074339902233344695" pos="-0.06330078084668134 0.12729620572711298 0.20743399022333447" type="box" mass="200" rgba="0.4 0.4 0.4 1"></geom>
<geom size="0.0417724260078509 0.03046246338754312 0.001276246865892172" pos="0.05053687352265129 -0.16366136713987467 0.20127624686589218" type="box" mass="200" rgba="0.4 0.4 0.4 1"></geom>
<geom size="0.021432317443754102 0.02300006268504014 0.007077890366598158" pos="-0.04772008840996045 0.002358698079731214 0.20707789036659818" type="box" mass="200" rgba="0.4 0.4 0.4 1"></geom>
<geom size="0.00673259256764981 0.0344215370190368 0.0007171218429658636" pos="-0.11242841376325544 0.0990467891251019 0.20071712184296586" type="box" mass="200" rgba="0.4 0.4 0.4 1"></geom>
<geom size="0.01576102858977463 0.0013768341575979054 0.004489305318774923" pos="0.08986207745545721 0.20803975072271436 0.20448930531877493" type="box" mass="200" rgba="0.4 0.4 0.4 1"></geom>
<geom size="0.04458551887237754 0.01301625291305861 0.009547428395512507" pos="-0.0767088509630052 -0.2735336196525171 0.20954742839551252" type="box" mass="200" rgba="0.4 0.4 0.4 1"></geom>
<geom size="0.01614569511449822 0.00957763122587195 0.0027873012952490646" pos="0.032891861179411785 0.057315002093427214 0.20278730129524908" type="box" mass="200" rgba="0.4 0.4 0.4 1"></geom>
<geom size="0.008451834679018493 0.020269013728392096 0.006245714124948624" pos="0.01445106887125469 0.03472953748148222 0.20624571412494863" type="box" mass="200" rgba="0.4 0.4 0.4 1"></geom>
<geom size="0.045814353962442114 0.03611845145402293 0.003086221557940588" pos="-0.011263396021978067 -0.23943540406086772 0.2030862215579406" type="box" mass="200" rgba="0.4 0.4 0.4 1"></geom>
<geom size="0.015597141269445863 0.04695687054684459 0.006965402590444824" pos="0.29482565398853716 -0.04944268485763559 0.20696540259044482" type="box" mass="200" rgba="0.4 0.4 0.4 1"></geom>
        </body>
        
        <body name="object0" pos="0.025 0.025 0.025">
            <joint name="object0:joint" type="free" damping="0.01"></joint>
            <geom size="0.027471632335881867 0.027471632335881867 0.027471632335881867" type="sphere" condim="3" name="object0" material="block_mat" mass="15.135129235781951" rgba="0.4 0.4 0.8 1"></geom>
            <site name="object0" pos="0 0 0" size="0.002 0.002 0.002" rgba="1 0 0 1" type="sphere"></site>
        </body>

        <body name="stick" pos="1.0 0.025 0.025">
            <joint name="stick:joint" type="free" damping="0.01"></joint>
            <geom size="0.4 0.015 0.015" type="box" condim="3" name="stick" material="block_mat" mass="2"></geom>
            <site name="stick" pos="-0.25 0 0" size="0.002 0.002 0.002" rgba="1 0 0 1" type="sphere"></site>
        </body>

        <light directional="true" ambient="0.2 0.2 0.2" diffuse="0.8 0.8 0.8" specular="0.3 0.3 0.3" castshadow="false" pos="0 0 4" dir="0 0 -1" name="light0"></light>
    </worldbody>
    
    <actuator>
        <position ctrllimited="true" ctrlrange="0 0.2" joint="robot0:l_gripper_finger_joint" kp="30000" name="robot0:l_gripper_finger_joint" user="1"></position>
        <position ctrllimited="true" ctrlrange="0 0.2" joint="robot0:r_gripper_finger_joint" kp="30000" name="robot0:r_gripper_finger_joint" user="1"></position>
    </actuator>
</mujoco>
    