<?xml version="1.0" encoding="utf-8"?>
<mujoco>
    <compiler angle="radian" coordinate="local" meshdir="../stls/fetch" texturedir="../textures"></compiler>
    <option timestep="0.002">
        <flag warmstart="enable"></flag>
    </option>

    <include file="shared.xml"></include>
    
    <worldbody>
        <geom name="floor0" pos="1.42 0.75 0" size="1.0 0.7 1" type="plane" condim="3" material="floor_mat"></geom>
        <body name="floor0" pos="1.42 0.75 0">
            <site name="target0" pos="0 0 0.5" size="0.02 0.02 0.02" rgba="1 0 0 1" type="sphere"></site>
        </body>

        <include file="robot.xml"></include>
        
        <body pos="1.65 0.75 0.2" name="table0">
            <geom size="0.5 0.45 0.2" type="box" mass="20000" material="table_mat"></geom><geom size="0.03147073989810062 0.047194517491128865 0.0037464289392732113" pos="0.13084546948988357 -0.29410874433004563 0.20374642893927322" type="box" mass="200" rgba="0.4 0.4 0.4 1"></geom>
<geom size="0.007569738216921071 0.038164498813890495 0.008275754489152506" pos="0.19924091104061598 0.1748865450468795 0.20827575448915253" type="box" mass="200" rgba="0.4 0.4 0.4 1"></geom>
<geom size="0.03866840617398058 0.0028246178902299156 0.0015352986574313503" pos="-0.0583663723638389 0.1156700603386448 0.20153529865743136" type="box" mass="200" rgba="0.4 0.4 0.4 1"></geom>
<geom size="0.04246205382186628 0.03593511471870861 0.0014174483306439402" pos="0.2944031362476551 -0.17992869717421173 0.20141744833064396" type="box" mass="200" rgba="0.4 0.4 0.4 1"></geom>
<geom size="0.033775048523812544 0.0038105603786429344 0.004378389494158441" pos="0.13830431622278405 -0.24580421765099728 0.20437838949415846" type="box" mass="200" rgba="0.4 0.4 0.4 1"></geom>
<geom size="0.04666031328380468 0.01613918073474869 0.002251803130222193" pos="-0.24489952348695776 0.06561809884948233 0.2022518031302222" type="box" mass="200" rgba="0.4 0.4 0.4 1"></geom>
<geom size="0.0067887314300472 0.042867854798531946 0.007242948935188912" pos="-0.2509284334447893 0.2980930783713441 0.20724294893518894" type="box" mass="200" rgba="0.4 0.4 0.4 1"></geom>
<geom size="0.04655053160387035 0.0497683054651148 0.0012304798380503904" pos="-0.16926156678227114 -5.466734083903191e-05 0.2012304798380504" type="box" mass="200" rgba="0.4 0.4 0.4 1"></geom>
<geom size="0.029361156664870047 0.010090504712241082 0.009513318962515317" pos="0.2844187909938321 -0.18547521007337242 0.20951331896251532" type="box" mass="200" rgba="0.4 0.4 0.4 1"></geom>
<geom size="0.024587125994321352 0.014566351112078293 0.005346469007685471" pos="-0.02334255005272834 -0.014266295986415045 0.2053464690076855" type="box" mass="200" rgba="0.4 0.4 0.4 1"></geom>
<geom size="0.043727913676311264 0.04907771496381769 0.000852391823973012" pos="-0.2829259113371302 0.09599795279397844 0.20085239182397302" type="box" mass="200" rgba="0.4 0.4 0.4 1"></geom>
<geom size="0.009397471945325538 0.0010739622869125997 0.007205377397142603" pos="0.1826224755588179 0.05405610457725796 0.20720537739714262" type="box" mass="200" rgba="0.4 0.4 0.4 1"></geom>
<geom size="0.025039147462640486 0.003172017343911308 0.005073037077867179" pos="0.0753740113208256 0.23773054952095424 0.2050730370778672" type="box" mass="200" rgba="0.4 0.4 0.4 1"></geom>
<geom size="0.022453965713286592 0.01231188803748207 0.00036805785122773693" pos="0.10959426081660983 0.19962214155539093 0.20036805785122774" type="box" mass="200" rgba="0.4 0.4 0.4 1"></geom>
<geom size="0.016003569343375715 0.03123343867357387 0.0066308431139950694" pos="-0.28600515097640833 -0.1500493932019374 0.20663084311399507" type="box" mass="200" rgba="0.4 0.4 0.4 1"></geom>
<geom size="0.03521505288348222 0.04999088664168321 0.0030649917046179156" pos="0.2547341474443359 -0.01090544337110233 0.20306499170461792" type="box" mass="200" rgba="0.4 0.4 0.4 1"></geom>
<geom size="0.00655944175842419 0.02508815658489848 0.003209667270964235" pos="0.10643943729566036 -0.28816399369016754 0.20320966727096423" type="box" mass="200" rgba="0.4 0.4 0.4 1"></geom>
<geom size="0.036520032224076154 0.0398794321312077 0.004140693210719648" pos="0.14658231008477024 0.2054057973454449 0.20414069321071965" type="box" mass="200" rgba="0.4 0.4 0.4 1"></geom>
<geom size="0.02154488909785913 0.03343088420426313 0.005879044079689974" pos="0.16672670812814805 -0.2810021898374305 0.20587904407969" type="box" mass="200" rgba="0.4 0.4 0.4 1"></geom>
<geom size="0.03477444752708019 0.01396770598979228 0.005997590404152276" pos="0.19467153141650434 0.0212385225072535 0.20599759040415228" type="box" mass="200" rgba="0.4 0.4 0.4 1"></geom>
<geom size="0.033444727433477435 0.040728912049444045 0.00046433620660072" pos="0.019842517267618764 -0.04363174077876608 0.20046433620660073" type="box" mass="200" rgba="0.4 0.4 0.4 1"></geom>
<geom size="0.03876200104329966 0.04855872525044576 0.004301588725295323" pos="-0.14002104141643484 0.07697981944963683 0.20430158872529533" type="box" mass="200" rgba="0.4 0.4 0.4 1"></geom>
<geom size="0.026982163829629563 0.023443791709296762 0.0007122601039327122" pos="-0.06273909867633165 0.044948531501424416 0.20071226010393273" type="box" mass="200" rgba="0.4 0.4 0.4 1"></geom>
<geom size="0.011137663432609263 0.033936959091829685 0.005040229728939792" pos="-0.11935032259064043 0.28571445081828034 0.20504022972893982" type="box" mass="200" rgba="0.4 0.4 0.4 1"></geom>
<geom size="0.021649509485600148 0.030208182052090807 0.008864010751135735" pos="0.06569172152638642 0.08104702965826849 0.20886401075113575" type="box" mass="200" rgba="0.4 0.4 0.4 1"></geom>
<geom size="0.022867552418944375 0.004728795514702613 0.003050601836871185" pos="-0.015680184133484487 -0.04010077713813415 0.2030506018368712" type="box" mass="200" rgba="0.4 0.4 0.4 1"></geom>
<geom size="0.03712533154781647 0.019422638676323985 0.008385217402607498" pos="-0.09668006497221135 0.19924345520869807 0.20838521740260751" type="box" mass="200" rgba="0.4 0.4 0.4 1"></geom>
        </body>
        
        <body name="object0" pos="0.025 0.025 0.025">
            <joint name="object0:joint" type="free" damping="0.01"></joint>
            <geom size="0.025918062434636756 0.025918062434636756 0.025918062434636756" type="sphere" condim="3" name="object0" material="block_mat" mass="1.7669936481564292" rgba="0.4 0.4 0.8 1"></geom>
            <site name="object0" pos="0 0 0" size="0.002 0.002 0.002" rgba="1 0 0 1" type="sphere"></site>
        </body>

        <body name="stick" pos="1.0 0.025 0.025">
            <joint name="stick:joint" type="free" damping="0.01"></joint>
            <geom size="0.4 0.015 0.015" type="box" condim="3" name="stick" material="block_mat" mass="2"></geom>
            <site name="stick" pos="-0.25 0 0" size="0.002 0.002 0.002" rgba="1 0 0 1" type="sphere"></site>
        </body>

        <light directional="true" ambient="0.2 0.2 0.2" diffuse="0.8 0.8 0.8" specular="0.3 0.3 0.3" castshadow="false" pos="0 0 4" dir="0 0 -1" name="light0"></light>
    </worldbody>
    
    <actuator>
        <position ctrllimited="true" ctrlrange="0 0.2" joint="robot0:l_gripper_finger_joint" kp="30000" name="robot0:l_gripper_finger_joint" user="1"></position>
        <position ctrllimited="true" ctrlrange="0 0.2" joint="robot0:r_gripper_finger_joint" kp="30000" name="robot0:r_gripper_finger_joint" user="1"></position>
    </actuator>
</mujoco>
    